{
  "openapi": "3.0.4",
  "info": {
    "title": "tarifkapida",
    "version": "1.0"
  },
  "paths": {
    "/api/Favorite/AddToFavorites": {
      "post": {
        "tags": [
          "Favorite"
        ],
        "parameters": [
          {
            "name": "userId",
            "in": "query",
            "schema": {
              "type": "integer",
              "format": "int32"
            }
          },
          {
            "name": "recipeId",
            "in": "query",
            "schema": {
              "type": "integer",
              "format": "int32"
            }
          }
        ],
        "responses": {
          "200": {
            "description": "OK"
          }
        }
      }
    },
    "/api/Favorite/RemoveFromFavorites": {
      "post": {
        "tags": [
          "Favorite"
        ],
        "parameters": [
          {
            "name": "userId",
            "in": "query",
            "schema": {
              "type": "integer",
              "format": "int32"
            }
          },
          {
            "name": "recipeId",
            "in": "query",
            "schema": {
              "type": "integer",
              "format": "int32"
            }
          }
        ],
        "responses": {
          "200": {
            "description": "OK"
          }
        }
      }
    },
    "/api/Favorite/GetUserFavorites/{userId}": {
      "get": {
        "tags": [
          "Favorite"
        ],
        "parameters": [
          {
            "name": "userId",
            "in": "path",
            "required": true,
            "schema": {
              "type": "integer",
              "format": "int32"
            }
          }
        ],
        "responses": {
          "200": {
            "description": "OK",
            "content": {
              "text/plain": {
                "schema": {
                  "type": "array",
                  "items": {
                    "$ref": "#/components/schemas/Recipe"
                  }
                }
              },
              "application/json": {
                "schema": {
                  "type": "array",
                  "items": {
                    "$ref": "#/components/schemas/Recipe"
                  }
                }
              },
              "text/json": {
                "schema": {
                  "type": "array",
                  "items": {
                    "$ref": "#/components/schemas/Recipe"
                  }
                }
              }
            }
          }
        }
      }
    },
    "/api/Favorite/IsFavorite": {
      "get": {
        "tags": [
          "Favorite"
        ],
        "parameters": [
          {
            "name": "userId",
            "in": "query",
            "schema": {
              "type": "integer",
              "format": "int32"
            }
          },
          {
            "name": "recipeId",
            "in": "query",
            "schema": {
              "type": "integer",
              "format": "int32"
            }
          }
        ],
        "responses": {
          "200": {
            "description": "OK"
          }
        }
      }
    },
    "/api/Favorite/ToggleFavorite": {
      "post": {
        "tags": [
          "Favorite"
        ],
        "parameters": [
          {
            "name": "userId",
            "in": "query",
            "schema": {
              "type": "integer",
              "format": "int32"
            }
          },
          {
            "name": "recipeId",
            "in": "query",
            "schema": {
              "type": "integer",
              "format": "int32"
            }
          }
        ],
        "responses": {
          "200": {
            "description": "OK"
          }
        }
      }
    },
    "/api/Favorite/SearchUserFavorites": {
      "get": {
        "tags": [
          "Favorite"
        ],
        "parameters": [
          {
            "name": "userId",
            "in": "query",
            "schema": {
              "type": "integer",
              "format": "int32"
            }
          },
          {
            "name": "searchTerm",
            "in": "query",
            "schema": {
              "type": "string"
            }
          }
        ],
        "responses": {
          "200": {
            "description": "OK",
            "content": {
              "text/plain": {
                "schema": {
                  "type": "array",
                  "items": {
                    "$ref": "#/components/schemas/Recipe"
                  }
                }
              },
              "application/json": {
                "schema": {
                  "type": "array",
                  "items": {
                    "$ref": "#/components/schemas/Recipe"
                  }
                }
              },
              "text/json": {
                "schema": {
                  "type": "array",
                  "items": {
                    "$ref": "#/components/schemas/Recipe"
                  }
                }
              }
            }
          }
        }
      }
    },
    "/api/Recipe/GetRecipes": {
      "get": {
        "tags": [
          "Recipe"
        ],
        "responses": {
          "200": {
            "description": "OK",
            "content": {
              "text/plain": {
                "schema": {
                  "type": "array",
                  "items": {
                    "$ref": "#/components/schemas/RecipeWithReviewsDto"
                  }
                }
              },
              "application/json": {
                "schema": {
                  "type": "array",
                  "items": {
                    "$ref": "#/components/schemas/RecipeWithReviewsDto"
                  }
                }
              },
              "text/json": {
                "schema": {
                  "type": "array",
                  "items": {
                    "$ref": "#/components/schemas/RecipeWithReviewsDto"
                  }
                }
              }
            }
          }
        }
      }
    },
    "/api/Recipe/GetRecipesTest": {
      "get": {
        "tags": [
          "Recipe"
        ],
        "responses": {
          "200": {
            "description": "OK",
            "content": {
              "text/plain": {
                "schema": {
                  "type": "array",
                  "items": {
                    "$ref": "#/components/schemas/Recipe"
                  }
                }
              },
              "application/json": {
                "schema": {
                  "type": "array",
                  "items": {
                    "$ref": "#/components/schemas/Recipe"
                  }
                }
              },
              "text/json": {
                "schema": {
                  "type": "array",
                  "items": {
                    "$ref": "#/components/schemas/Recipe"
                  }
                }
              }
            }
          }
        }
      }
    },
    "/api/Recipe/GetRecipeById/{recipeId}": {
      "get": {
        "tags": [
          "Recipe"
        ],
        "parameters": [
          {
            "name": "recipeId",
            "in": "path",
            "required": true,
            "schema": {
              "type": "integer",
              "format": "int32"
            }
          }
        ],
        "responses": {
          "200": {
            "description": "OK",
            "content": {
              "text/plain": {
                "schema": {
                  "$ref": "#/components/schemas/Recipe"
                }
              },
              "application/json": {
                "schema": {
                  "$ref": "#/components/schemas/Recipe"
                }
              },
              "text/json": {
                "schema": {
                  "$ref": "#/components/schemas/Recipe"
                }
              }
            }
          }
        }
      }
    },
    "/api/Recipe/CreateRecipe": {
      "post": {
        "tags": [
          "Recipe"
        ],
        "requestBody": {
          "content": {
            "application/json": {
              "schema": {
                "$ref": "#/components/schemas/Recipe"
              }
            },
            "text/json": {
              "schema": {
                "$ref": "#/components/schemas/Recipe"
              }
            },
            "application/*+json": {
              "schema": {
                "$ref": "#/components/schemas/Recipe"
              }
            }
          }
        },
        "responses": {
          "200": {
            "description": "OK",
            "content": {
              "text/plain": {
                "schema": {
                  "$ref": "#/components/schemas/Recipe"
                }
              },
              "application/json": {
                "schema": {
                  "$ref": "#/components/schemas/Recipe"
                }
              },
              "text/json": {
                "schema": {
                  "$ref": "#/components/schemas/Recipe"
                }
              }
            }
          }
        }
      }
    },
    "/api/Recipe/UpdateRecipe": {
      "put": {
        "tags": [
          "Recipe"
        ],
        "requestBody": {
          "content": {
            "application/json": {
              "schema": {
                "$ref": "#/components/schemas/Recipe"
              }
            },
            "text/json": {
              "schema": {
                "$ref": "#/components/schemas/Recipe"
              }
            },
            "application/*+json": {
              "schema": {
                "$ref": "#/components/schemas/Recipe"
              }
            }
          }
        },
        "responses": {
          "200": {
            "description": "OK",
            "content": {
              "text/plain": {
                "schema": {
                  "$ref": "#/components/schemas/Recipe"
                }
              },
              "application/json": {
                "schema": {
                  "$ref": "#/components/schemas/Recipe"
                }
              },
              "text/json": {
                "schema": {
                  "$ref": "#/components/schemas/Recipe"
                }
              }
            }
          }
        }
      }
    },
    "/api/Recipe/DeleteRecipe/{recipeId}": {
      "post": {
        "tags": [
          "Recipe"
        ],
        "parameters": [
          {
            "name": "recipeId",
            "in": "query",
            "schema": {
              "type": "integer",
              "format": "int32"
            }
          },
          {
            "name": "recipeId",
            "in": "path",
            "required": true,
            "schema": {
              "type": "string"
            }
          }
        ],
        "responses": {
          "200": {
            "description": "OK"
          }
        }
      }
    },
    "/api/Recipe/SearchRecipes": {
      "get": {
        "tags": [
          "Recipe"
        ],
        "parameters": [
          {
            "name": "searchTerm",
            "in": "query",
            "schema": {
              "type": "string"
            }
          }
        ],
        "responses": {
          "200": {
            "description": "OK",
            "content": {
              "text/plain": {
                "schema": {
                  "type": "array",
                  "items": {
                    "$ref": "#/components/schemas/Recipe"
                  }
                }
              },
              "application/json": {
                "schema": {
                  "type": "array",
                  "items": {
                    "$ref": "#/components/schemas/Recipe"
                  }
                }
              },
              "text/json": {
                "schema": {
                  "type": "array",
                  "items": {
                    "$ref": "#/components/schemas/Recipe"
                  }
                }
              }
            }
          }
        }
      }
    },
    "/api/Recipe/GetRecipesByUserId/{userId}": {
      "get": {
        "tags": [
          "Recipe"
        ],
        "parameters": [
          {
            "name": "userId",
            "in": "path",
            "required": true,
            "schema": {
              "type": "integer",
              "format": "int32"
            }
          }
        ],
        "responses": {
          "200": {
            "description": "OK",
            "content": {
              "text/plain": {
                "schema": {
                  "type": "array",
                  "items": {
                    "$ref": "#/components/schemas/Recipe"
                  }
                }
              },
              "application/json": {
                "schema": {
                  "type": "array",
                  "items": {
                    "$ref": "#/components/schemas/Recipe"
                  }
                }
              },
              "text/json": {
                "schema": {
                  "type": "array",
                  "items": {
                    "$ref": "#/components/schemas/Recipe"
                  }
                }
              }
            }
          }
        }
      }
    },
    "/api/Review/GetReviews": {
      "get": {
        "tags": [
          "Review"
        ],
        "responses": {
          "200": {
            "description": "OK",
            "content": {
              "text/plain": {
                "schema": {
                  "type": "array",
                  "items": {
                    "$ref": "#/components/schemas/Review"
                  }
                }
              },
              "application/json": {
                "schema": {
                  "type": "array",
                  "items": {
                    "$ref": "#/components/schemas/Review"
                  }
                }
              },
              "text/json": {
                "schema": {
                  "type": "array",
                  "items": {
                    "$ref": "#/components/schemas/Review"
                  }
                }
              }
            }
          }
        }
      }
    },
    "/api/Review/GetReviewById/{reviewId}": {
      "get": {
        "tags": [
          "Review"
        ],
        "parameters": [
          {
            "name": "reviewId",
            "in": "path",
            "required": true,
            "schema": {
              "type": "integer",
              "format": "int32"
            }
          }
        ],
        "responses": {
          "200": {
            "description": "OK",
            "content": {
              "text/plain": {
                "schema": {
                  "$ref": "#/components/schemas/Review"
                }
              },
              "application/json": {
                "schema": {
                  "$ref": "#/components/schemas/Review"
                }
              },
              "text/json": {
                "schema": {
                  "$ref": "#/components/schemas/Review"
                }
              }
            }
          }
        }
      }
    },
    "/api/Review/CreateReview": {
      "post": {
        "tags": [
          "Review"
        ],
        "requestBody": {
          "content": {
            "application/json": {
              "schema": {
                "$ref": "#/components/schemas/Review"
              }
            },
            "text/json": {
              "schema": {
                "$ref": "#/components/schemas/Review"
              }
            },
            "application/*+json": {
              "schema": {
                "$ref": "#/components/schemas/Review"
              }
            }
          }
        },
        "responses": {
          "200": {
            "description": "OK",
            "content": {
              "text/plain": {
                "schema": {
                  "$ref": "#/components/schemas/Review"
                }
              },
              "application/json": {
                "schema": {
                  "$ref": "#/components/schemas/Review"
                }
              },
              "text/json": {
                "schema": {
                  "$ref": "#/components/schemas/Review"
                }
              }
            }
          }
        }
      }
    },
    "/api/Review/UpdateReview": {
      "put": {
        "tags": [
          "Review"
        ],
        "requestBody": {
          "content": {
            "application/json": {
              "schema": {
                "$ref": "#/components/schemas/Review"
              }
            },
            "text/json": {
              "schema": {
                "$ref": "#/components/schemas/Review"
              }
            },
            "application/*+json": {
              "schema": {
                "$ref": "#/components/schemas/Review"
              }
            }
          }
        },
        "responses": {
          "200": {
            "description": "OK",
            "content": {
              "text/plain": {
                "schema": {
                  "$ref": "#/components/schemas/Review"
                }
              },
              "application/json": {
                "schema": {
                  "$ref": "#/components/schemas/Review"
                }
              },
              "text/json": {
                "schema": {
                  "$ref": "#/components/schemas/Review"
                }
              }
            }
          }
        }
      }
    },
    "/api/Review/DeleteReview/{reviewId}": {
      "post": {
        "tags": [
          "Review"
        ],
        "parameters": [
          {
            "name": "reviewId",
            "in": "query",
            "schema": {
              "type": "integer",
              "format": "int32"
            }
          },
          {
            "name": "reviewId",
            "in": "path",
            "required": true,
            "schema": {
              "type": "string"
            }
          }
        ],
        "responses": {
          "200": {
            "description": "OK"
          }
        }
      }
    },
    "/api/User/GetUsers": {
      "get": {
        "tags": [
          "User"
        ],
        "responses": {
          "200": {
            "description": "OK",
            "content": {
              "text/plain": {
                "schema": {
                  "type": "array",
                  "items": {
                    "$ref": "#/components/schemas/Users"
                  }
                }
              },
              "application/json": {
                "schema": {
                  "type": "array",
                  "items": {
                    "$ref": "#/components/schemas/Users"
                  }
                }
              },
              "text/json": {
                "schema": {
                  "type": "array",
                  "items": {
                    "$ref": "#/components/schemas/Users"
                  }
                }
              }
            }
          }
        }
      }
    },
    "/api/User/Login": {
      "post": {
        "tags": [
          "User"
        ],
        "requestBody": {
          "content": {
            "application/json": {
              "schema": {
                "$ref": "#/components/schemas/LoginRequest"
              }
            },
            "text/json": {
              "schema": {
                "$ref": "#/components/schemas/LoginRequest"
              }
            },
            "application/*+json": {
              "schema": {
                "$ref": "#/components/schemas/LoginRequest"
              }
            }
          }
        },
        "responses": {
          "200": {
            "description": "OK",
            "content": {
              "text/plain": {
                "schema": {
                  "$ref": "#/components/schemas/Users"
                }
              },
              "application/json": {
                "schema": {
                  "$ref": "#/components/schemas/Users"
                }
              },
              "text/json": {
                "schema": {
                  "$ref": "#/components/schemas/Users"
                }
              }
            }
          }
        }
      }
    },
    "/api/User/GetUserById/{userId}": {
      "get": {
        "tags": [
          "User"
        ],
        "parameters": [
          {
            "name": "userId",
            "in": "path",
            "required": true,
            "schema": {
              "type": "integer",
              "format": "int32"
            }
          }
        ],
        "responses": {
          "200": {
            "description": "OK",
            "content": {
              "text/plain": {
                "schema": {
                  "$ref": "#/components/schemas/Users"
                }
              },
              "application/json": {
                "schema": {
                  "$ref": "#/components/schemas/Users"
                }
              },
              "text/json": {
                "schema": {
                  "$ref": "#/components/schemas/Users"
                }
              }
            }
          }
        }
      }
    },
    "/api/User/CreateUser": {
      "post": {
        "tags": [
          "User"
        ],
        "requestBody": {
          "content": {
            "application/json": {
              "schema": {
                "$ref": "#/components/schemas/Users"
              }
            },
            "text/json": {
              "schema": {
                "$ref": "#/components/schemas/Users"
              }
            },
            "application/*+json": {
              "schema": {
                "$ref": "#/components/schemas/Users"
              }
            }
          }
        },
        "responses": {
          "200": {
            "description": "OK",
            "content": {
              "text/plain": {
                "schema": {
                  "$ref": "#/components/schemas/Users"
                }
              },
              "application/json": {
                "schema": {
                  "$ref": "#/components/schemas/Users"
                }
              },
              "text/json": {
                "schema": {
                  "$ref": "#/components/schemas/Users"
                }
              }
            }
          }
        }
      }
    },
    "/api/User/UpdateUser": {
      "put": {
        "tags": [
          "User"
        ],
        "requestBody": {
          "content": {
            "application/json": {
              "schema": {
                "$ref": "#/components/schemas/Users"
              }
            },
            "text/json": {
              "schema": {
                "$ref": "#/components/schemas/Users"
              }
            },
            "application/*+json": {
              "schema": {
                "$ref": "#/components/schemas/Users"
              }
            }
          }
        },
        "responses": {
          "200": {
            "description": "OK",
            "content": {
              "text/plain": {
                "schema": {
                  "$ref": "#/components/schemas/Users"
                }
              },
              "application/json": {
                "schema": {
                  "$ref": "#/components/schemas/Users"
                }
              },
              "text/json": {
                "schema": {
                  "$ref": "#/components/schemas/Users"
                }
              }
            }
          }
        }
      }
    },
    "/api/User/DeleteUser": {
      "post": {
        "tags": [
          "User"
        ],
        "parameters": [
          {
            "name": "userId",
            "in": "query",
            "schema": {
              "type": "integer",
              "format": "int32"
            }
          }
        ],
        "responses": {
          "200": {
            "description": "OK"
          }
        }
      }
    },
    "/api/User/Register": {
      "post": {
        "tags": [
          "User"
        ],
        "requestBody": {
          "content": {
            "application/json": {
              "schema": {
                "$ref": "#/components/schemas/RegisterRequest"
              }
            },
            "text/json": {
              "schema": {
                "$ref": "#/components/schemas/RegisterRequest"
              }
            },
            "application/*+json": {
              "schema": {
                "$ref": "#/components/schemas/RegisterRequest"
              }
            }
          }
        },
        "responses": {
          "200": {
            "description": "OK"
          }
        }
      }
    }
  },
  "components": {
    "schemas": {
      "LoginRequest": {
        "type": "object",
        "properties": {
          "username": {
            "type": "string",
            "nullable": true
          },
          "password": {
            "type": "string",
            "nullable": true
          }
        },
        "additionalProperties": false
      },
      "Recipe": {
        "type": "object",
        "properties": {
          "recipeId": {
            "type": "integer",
            "format": "int32"
          },
          "recipeName": {
            "type": "string",
            "nullable": true
          },
          "recipeDescription": {
            "type": "string",
            "nullable": true
          },
          "recipeIngredients": {
            "type": "string",
            "nullable": true
          },
          "recipeInstructions": {
            "type": "string",
            "nullable": true
          },
          "recipeImageUrl": {
            "type": "string",
            "nullable": true
          },
          "userId": {
            "type": "integer",
            "format": "int32",
            "nullable": true
          },
          "recipeCreatedAt": {
            "type": "string",
            "format": "date-time",
            "nullable": true
          },
          "recipeUpdatedAt": {
            "type": "string",
            "format": "date-time",
            "nullable": true
          },
          "user": {
            "$ref": "#/components/schemas/Users"
          },
          "reviews": {
            "type": "array",
            "items": {
              "$ref": "#/components/schemas/Review"
            },
            "nullable": true
          },
          "reviewId": {
            "type": "integer",
            "format": "int32"
          },
          "favoriteCount": {
            "type": "integer",
            "format": "int32"
          }
        },
        "additionalProperties": false
      },
      "RecipeWithReviewsDto": {
        "type": "object",
        "properties": {
          "recipeId": {
            "type": "integer",
            "format": "int32"
          },
          "recipeName": {
            "type": "string",
            "nullable": true
          },
          "recipeDescription": {
            "type": "string",
            "nullable": true
          },
          "recipeIngredients": {
            "type": "string",
            "nullable": true
          },
          "recipeInstructions": {
            "type": "string",
            "nullable": true
          },
          "recipeImageUrl": {
            "type": "string",
            "nullable": true
          },
          "userId": {
            "type": "integer",
            "format": "int32",
            "nullable": true
          },
          "recipeCreatedAt": {
            "type": "string",
            "format": "date-time",
            "nullable": true
          },
          "recipeUpdatedAt": {
            "type": "string",
            "format": "date-time",
            "nullable": true
          },
          "reviews": {
            "type": "array",
            "items": {
              "$ref": "#/components/schemas/ReviewDto"
            },
            "nullable": true
          },
          "reviewCount": {
            "type": "integer",
            "format": "int32"
          },
          "averageRating": {
            "type": "number",
            "format": "double"
          }
        },
        "additionalProperties": false
      },
      "RegisterRequest": {
        "required": [
          "confirmPassword",
          "email",
          "password",
          "username"
        ],
        "type": "object",
        "properties": {
          "username": {
            "minLength": 1,
            "type": "string"
          },
          "email": {
            "minLength": 1,
            "type": "string",
            "format": "email"
          },
          "password": {
            "minLength": 6,
            "type": "string"
          },
          "confirmPassword": {
            "minLength": 1,
            "type": "string"
          }
        },
        "additionalProperties": false
      },
      "Review": {
        "type": "object",
        "properties": {
          "reviewId": {
            "type": "integer",
            "format": "int32"
          },
          "recipeId": {
            "type": "integer",
            "format": "int32"
          },
          "recipe": {
            "$ref": "#/components/schemas/Recipe"
          },
          "userId": {
            "type": "integer",
            "format": "int32"
          },
          "user": {
            "$ref": "#/components/schemas/Users"
          },
          "reviewText": {
            "type": "string",
            "nullable": true
          },
          "rating": {
            "type": "integer",
            "format": "int32"
          },
          "reviewCreatedAt": {
            "type": "string",
            "format": "date-time"
          },
          "reviewUpdatedAt": {
            "type": "string",
            "format": "date-time"
          }
        },
        "additionalProperties": false
      },
      "ReviewDto": {
        "type": "object",
        "properties": {
          "reviewId": {
            "type": "integer",
            "format": "int32"
          },
          "recipeId": {
            "type": "integer",
            "format": "int32"
          },
          "userId": {
            "type": "integer",
            "format": "int32"
          },
          "reviewText": {
            "type": "string",
            "nullable": true
          },
          "rating": {
            "type": "integer",
            "format": "int32"
          },
          "reviewCreatedAt": {
            "type": "string",
            "format": "date-time"
          },
          "reviewUpdatedAt": {
            "type": "string",
            "format": "date-time"
          },
          "username": {
            "type": "string",
            "nullable": true
          }
        },
        "additionalProperties": false
      },
      "Users": {
        "type": "object",
        "properties": {
          "userId": {
            "type": "integer",
            "format": "int32"
          },
          "username": {
            "type": "string",
            "nullable": true
          },
          "password": {
            "type": "string",
            "nullable": true
          },
          "email": {
            "type": "string",
            "nullable": true
          },
          "reviews": {
            "type": "array",
            "items": {
              "$ref": "#/components/schemas/Review"
            },
            "nullable": true
          },
          "recipes": {
            "type": "array",
            "items": {
              "$ref": "#/components/schemas/Recipe"
            },
            "nullable": true
          }
        },
        "additionalProperties": false
      }
    }
  }
}